Workbook

Sheet Summary
B2: Apple Messages for Business
B3: Experience Review, validation summary
B4: Fill in the Checklist tab. This tab rolls up automatically. Scope comes from the Scope tab.
B6: Status breakdown
B7: Status | C7: Count
B8: Not Started | C8: =COUNTIF(Checklist!$I$3:$I$128,"Not Started") -> 114
B9: In Progress | C9: =COUNTIF(Checklist!$I$3:$I$128,"In Progress") -> 0
B10: Pass | C10: =COUNTIF(Checklist!$I$3:$I$128,"Pass") -> 0
B11: Fail | C11: =COUNTIF(Checklist!$I$3:$I$128,"Fail") -> 0
B12: Blocked | C12: =COUNTIF(Checklist!$I$3:$I$128,"Blocked") -> 0
B13: N/A | C13: =COUNTIF(Checklist!$I$3:$I$128,"N/A") -> 0
B14: Requires client testing | C14: =COUNTIF(Checklist!$I$3:$I$128,"Requires client testing") -> 0
B15: TBD | C15: =COUNTIF(Checklist!$I$3:$I$128,"TBD") -> 0
B16: Total test cases | C16: =COUNTA(Checklist!$B$3:$B$128) -> 114
B17: Pass rate of tested (Pass + Fail) | C17: =IFERROR(COUNTIF(Checklist!$I$3:$I$128,"Pass")/(COUNTIF(Checklist!$I$3:$I$128,"Pass")+COUNTIF(Checklist!$I$3:$I$128,"Fail")),0) -> 0
B19: Non-negotiable gate
B20: Failed or blocked non-negotiables | C20: =COUNTIFS(Checklist!$H$3:$H$128,"Non negotiable",Checklist!$I$3:$I$128,"Fail")+COUNTIFS(Checklist!$H$3:$H$128,"Non negotiable",Checklist!$I$3:$I$128,"Blocked") -> 0
B21: Any non-zero count here means the submission is not ready. These are checked on every Apple review.
B23: Coverage
B24: Rows in scope (not N/A) | C24: =COUNTA(Checklist!$B$3:$B$128)-COUNTIF(Checklist!$I$3:$I$128,"N/A") -> 114
B25: Rows marked N/A | C25: =COUNTIF(Checklist!$I$3:$I$128,"N/A") -> 0
B26: Rows with recording evidence logged | C26: =COUNTA(Checklist!$J$3:$J$128) -> 0
B27: In-scope rows still without evidence | C27: =COUNTA(Checklist!$B$3:$B$128)-COUNTIF(Checklist!$I$3:$I$128,"N/A")-COUNTA(Checklist!$J$3:$J$128) -> 114
B29: Fails by severity
B30: Non negotiable | C30: =COUNTIFS(Checklist!$H$3:$H$128,"Non negotiable",Checklist!$I$3:$I$128,"Fail") -> 0
B31: Apple standard | C31: =COUNTIFS(Checklist!$H$3:$H$128,"Apple standard",Checklist!$I$3:$I$128,"Fail") -> 0
B32: Field | C32: =COUNTIFS(Checklist!$H$3:$H$128,"Field",Checklist!$I$3:$I$128,"Fail") -> 0
B34: Fails by category
B35: Category | C35: Fail count
B36: 0. Final Gate (checked on every Apple review, see the Legend for Apple's five) | C36: =COUNTIFS(Checklist!$A$3:$A$128,"0. Final Gate (checked on every Apple review, see the Legend for Apple's five)",Checklist!$I$3:$I$128,"Fail") -> 0
B37: 1. Pre-Test and Review Readiness | C37: =COUNTIFS(Checklist!$A$3:$A$128,"1. Pre-Test and Review Readiness",Checklist!$I$3:$I$128,"Fail") -> 0
B38: 2. Entry Points and Passable Context | C38: =COUNTIFS(Checklist!$A$3:$A$128,"2. Entry Points and Passable Context",Checklist!$I$3:$I$128,"Fail") -> 0
B39: 3. Agent Identification, Honesty and Triage | C39: =COUNTIFS(Checklist!$A$3:$A$128,"3. Agent Identification, Honesty and Triage",Checklist!$I$3:$I$128,"Fail") -> 0
B40: 4. Core Messaging, Rich Links and Close | C40: =COUNTIFS(Checklist!$A$3:$A$128,"4. Core Messaging, Rich Links and Close",Checklist!$I$3:$I$128,"Fail") -> 0
B41: 5. Interactive Features | C41: =COUNTIFS(Checklist!$A$3:$A$128,"5. Interactive Features",Checklist!$I$3:$I$128,"Fail") -> 0
B42: 6. Attachments and Wallet Passes | C42: =COUNTIFS(Checklist!$A$3:$A$128,"6. Attachments and Wallet Passes",Checklist!$I$3:$I$128,"Fail") -> 0
B43: 7. Authentication, Apple Pay and Personal Data | C43: =COUNTIFS(Checklist!$A$3:$A$128,"7. Authentication, Apple Pay and Personal Data",Checklist!$I$3:$I$128,"Fail") -> 0
B44: 8. Device Capability and Fallback | C44: =COUNTIFS(Checklist!$A$3:$A$128,"8. Device Capability and Fallback",Checklist!$I$3:$I$128,"Fail") -> 0
B45: 9. Human Escalation and Live Agent Handoff | C45: =COUNTIFS(Checklist!$A$3:$A$128,"9. Human Escalation and Live Agent Handoff",Checklist!$I$3:$I$128,"Fail") -> 0
B46: 10. Policy, Consent and Conversational Design | C46: =COUNTIFS(Checklist!$A$3:$A$128,"10. Policy, Consent and Conversational Design",Checklist!$I$3:$I$128,"Fail") -> 0
B47: 11. Recording and Submission Prep | C47: =COUNTIFS(Checklist!$A$3:$A$128,"11. Recording and Submission Prep",Checklist!$I$3:$I$128,"Fail") -> 0
B48: 12. Entry Point Configuration, Buttons and Readiness | C48: =COUNTIFS(Checklist!$A$3:$A$128,"12. Entry Point Configuration, Buttons and Readiness",Checklist!$I$3:$I$128,"Fail") -> 0

Sheet Checklist
A1: Section | B1: Ref | C1: Test case | D1: Test steps | E1: Expected result | F1: Rule ref | G1: Applies when | H1: Severity | I1: Status | J1: Evidence (video + mm:ss) | K1: Actual result | L1: Comments
A2: 0. Final Gate (checked on every Apple review, see the Legend for Apple's five)
A3: 0. Final Gate (checked on every Apple review, see the Legend for Apple's five) | B3: 0.1 | C3: Reachable escalation | D3: Confirm a live agent connection is reachable within stated hours, OR the exempted callback or in conversation message path is offered and works end to end (see Section 9). | E3: Escalation path is reachable and functional. | F3: 2.3 | G3: Always | H3: Non negotiable | I3: Not Started
A4: 0. Final Gate (checked on every Apple review, see the Legend for Apple's five) | B4: 0.2 | C4: Leave Conversation respected | D4: End the conversation via Leave Conversation, then attempt to send from both the bot and a live agent. | E4: Both bot and human agent are blocked from sending; the business cannot re-engage until the user restarts. | F4: 2.9 | G4: Always | H4: Non negotiable | I4: Not Started
A5: 0. Final Gate (checked on every Apple review, see the Legend for Apple's five) | B5: 0.3 | C5: No forbidden or restricted platform wording | D5: Review every piece of bot copy, template text, interface label, localisation bundle, onboarding copy and spoken narration in the recording. | E5: No use of "iMessage", "AMB", "Apple Chat", "chat" or "text" as a channel name, and no wording implying Apple endorses the brand. Correct product naming throughout. | F5: 2.12 | G5: Always | H5: Non negotiable | I5: Not Started
A6: 0. Final Gate (checked on every Apple review, see the Legend for Apple's five) | B6: 0.4 | C6: Opt-out works end to end | D6: Trigger STOP / UNSUBSCRIBE / QUIT from an active, opted-in conversation. | E6: Both bot and live agent stop sending immediately; opt-out applies brand-wide, not just the current thread; re-engagement requires a fresh opt-in. | F6: 2.9 | G6: Always | H6: Non negotiable | I6: Not Started
A7: 1. Pre-Test and Review Readiness
A8: 1. Pre-Test and Review Readiness | B8: 1.1 | C8: Apple Messages for Business account connected and delivering | D8: Confirm the account is connected and send a test message. | E8: Message delivery is confirmed end to end. | F8: Doc 1 s4 | G8: Always | H8: Apple standard | I8: Not Started
A9: 1. Pre-Test and Review Readiness | B9: 1.2 | C9: Commercial account access restricted | D9: Check Account Testing then Advanced settings. | E9: Access is restricted to authorized Apple IDs used for testing. | F9: Doc 1 s4 | G9: Always | H9: Apple standard | I9: Not Started
A10: 1. Pre-Test and Review Readiness | B10: 1.3 | C10: All registered use cases are testable | D10: Cross-check the approved use case list on Appendix A against scenarios available in the test build. | E10: Every submitted use case has a corresponding, working flow in the test environment. | F10: Doc 1 s4 | G10: Always | H10: Apple standard | I10: Not Started
A11: 1. Pre-Test and Review Readiness | B11: 1.4 | C11: All entry points are functional | D11: Test each entry point marked in scope on Appendix A (URL button, Message Suggest, Apple Maps, Wallet, QR or App Store link, Business Invitation, IVR deflection, social). | E11: Each entry point opens a Messages conversation with the correct business account and correct routing context. | F11: 2.13 | G11: Always | H11: Apple standard | I11: Not Started
A12: 1. Pre-Test and Review Readiness | B12: 1.5 | C12: Agents trained, and an introduction script is defined | D12: Confirm with the client that live agent staff have been briefed, and review the written agent introduction script. | E12: Agents are prepared and trained for the channel and the relevant use cases, and a consistent introduction script exists. | F12: 2.3 | G12: Live agent in scope | H12: Apple standard | I12: Not Started
A13: 1. Pre-Test and Review Readiness | B13: 1.6 | C13: Tested on macOS as well as iPhone | D13: Run the primary use case from the Messages app on a Mac signed in to the same Apple ID. | E13: The experience works on macOS. iPhone is the priority platform, but macOS is also tested before submission. | F13: Doc 1 s4 | G13: Always | H13: Apple standard | I13: Not Started
A14: 1. Pre-Test and Review Readiness | B14: 1.7 | C14: Baseline metrics planned before launch | D14: Confirm with the client which metrics are captured and from when. | E14: Response times, resolution rates and satisfaction baselines are planned before launch, not after. | F14: 2.15 | G14: Always | H14: Apple standard | I14: Not Started
A15: 2. Entry Points and Passable Context
A16: 2. Entry Points and Passable Context | B16: 2.1 | C16: Entry point routing lands in the correct flow | D16: Open the conversation from each of the brand's registered entry points (for example two different QR codes for two different stores or intents). | E16: Each entry point routes to the correct, distinct flow, not the same generic flow regardless of source. | F16: 2.13 | G16: Always | H16: Apple standard | I16: Not Started
A17: 2. Entry Points and Passable Context | B17: 2.2 | C17: Bot confirms context received from entry point | D17: Open a conversation from an entry point carrying routing context (store, product or campaign reference). | E17: The opening message reflects the context received, for example "I see you're asking about [Store or Product X]", rather than a generic greeting. | F17: 2.4 | G17: Any entry point carrying context | H17: Apple standard | I17: Not Started
A18: 2. Entry Points and Passable Context | B18: 2.3 | C18: Business Invitation opt-in gate and decline handling | D18: Attempt to send a Business Invitation to a number that has not opted in; then send a valid test invite and respond "No" or decline. | E18: Platform requires opt-in coverage before sending; a decline is correctly registered and that user is not messaged again. | F18: 2.9 | G18: Business Invitations in scope | H18: Apple standard | I18: Not Started
A19: 2. Entry Points and Passable Context | B19: 2.4 | C19: Invitation opt-out present in every Business Update | D19: Review every Business Invitation and Business Update message the brand sends. | E19: Opt-out instructions appear in every single Business Update message, not just the first. | F19: 2.9 | G19: Business Invitations in scope | H19: Apple standard | I19: Not Started
A20: 2. Entry Points and Passable Context | B20: 2.5 | C20: A "Yes" on a Business Invitation is followed by a welcome that explains what was accepted | D20: Accept a Business Invitation and read the next message. | E20: An agent message welcomes the customer and states plainly what they signed up for, for example what notifications will be sent and how often. | F20: 2.6 | G20: Business Invitations in scope | H20: Apple standard | I20: Not Started
A21: 3. Agent Identification, Honesty and Triage
A22: 3. Agent Identification, Honesty and Triage | B22: 3.1 | C22: First response within 5 seconds, with typing indicator | D22: Send the first message of a new conversation and time the automated reply. | E22: A typing indicator appears first, then the automated response arrives within 5 seconds total. | F22: 2.4 | G22: Always | H22: Non negotiable | I22: Not Started
A23: 3. Agent Identification, Honesty and Triage | B23: 3.2 | C23: Bot self-identifies as automated on entry | D23: Review the opening automated message. | E23: Message clearly and plainly states it is an automated agent, not implied or buried. | F23: 2.4 | G23: Always | H23: Non negotiable | I23: Not Started
A24: 3. Agent Identification, Honesty and Triage | B24: 3.3 | C24: The opener states the assistant's name and what it covers | D24: Read the opening message after the disclosure. | E24: The opener names the assistant and states its scope, for example "I'm [NAME], here to help with orders, delivery and returns". Disclosure followed only by "what can we help you with?" does not satisfy this. | F24: 2.4 | G24: Always | H24: Apple standard | I24: Not Started
A25: 3. Agent Identification, Honesty and Triage | B25: 3.4 | C25: Bot answers truthfully when asked if it is a bot | D25: At multiple points in the conversation ask directly: "are you a bot?", "am I talking to a real person?", "are you AI?" | E25: Bot always answers truthfully that it is automated. It never claims to be human or dodges the question. | F25: 2.4 | G25: Always | H25: Non negotiable | I25: Not Started
A26: 3. Agent Identification, Honesty and Triage | B26: 3.5 | C26: Typing indicator before every outbound message, including rich features | D26: Step through a multi-message bot flow, including back-to-back sequences with no user input between them (enrollment confirmations, status updates, summaries, quick replies, forms). | E26: A typing indicator appears before every single outbound payload, not just the first, including one-off notifications, attachments, rich and interactive bubbles, the Authentication card and Apple Pay. | F26: 2.3 | G26: Always | H26: Non negotiable | I26: Not Started
A27: 3. Agent Identification, Honesty and Triage | B27: 3.6 | C27: Typing indicator never hangs or misleads | D27: Have a live agent leave a typing indicator active for an extended period without sending. | E27: Indicator resolves or refreshes sensibly rather than hanging indefinitely and implying an imminent reply that never comes. | F27: 2.3 | G27: Always | H27: Apple standard | I27: Not Started
A28: 3. Agent Identification, Honesty and Triage | B28: 3.7 | C28: Live agent messages also carry a typing indicator | D28: During a live agent exchange, watch the customer device while the agent composes. | E28: The typing indicator appears on the customer side for agent messages as well as bot messages. | F28: 2.3 | G28: Live agent in scope | H28: Apple standard | I28: Not Started
A29: 3. Agent Identification, Honesty and Triage | B29: 3.8 | C29: Triage menu appears when intent is unclear | D29: Send an ambiguous opening message such as "hi". | E29: Bot offers a Quick Reply triage menu of up to five options instead of guessing or forcing free text. | F29: 2.4 | G29: Always | H29: Apple standard | I29: Not Started
A30: 3. Agent Identification, Honesty and Triage | B30: 3.9 | C30: Triage menu leads with the most common options | D30: Compare the order of the menu options against real demand data. | E30: The most common reasons customers make contact appear first, and the list reflects real demand rather than an internal org chart. | F30: 2.5 | G30: Always | H30: Apple standard | I30: Not Started
A31: 3. Agent Identification, Honesty and Triage | B31: 3.10 | C31: A clearly written intent is answered rather than overridden by the menu | D31: Open the conversation with a specific, unambiguous request. | E31: The bot answers what was asked. It does not discard the stated intent and present the triage menu instead. | F31: 2.4 | G31: Always | H31: Apple standard | I31: Not Started
A32: 3. Agent Identification, Honesty and Triage | B32: 3.11 | C32: A route to a person appears on every menu | D32: Review every triage menu and sub-menu in the experience. | E32: Each menu includes an option to reach a person, or the agreed alternative path. | F32: 2.4 | G32: Always | H32: Apple standard | I32: Not Started
A33: 3. Agent Identification, Honesty and Triage | B33: 3.12 | C33: Triage is never more than two levels deep | D33: Walk the deepest menu path in the design. | E33: No path requires more than two menu selections before reaching a task or a person. | F33: 2.4 | G33: Always | H33: Apple standard | I33: Not Started
... A41: 3. Agent Identification, Honesty and Triage | B41: 3.20 | C41: Welcome message tone matches brand | D41: Review the welcome and greeting copy against brand voice guidelines. | E41: Tone is warm, on-brand, and not robotic or legalistic. | F41: 3.6 | G41: Always | H41: Field | I41: Not Started
A42: 4. Core Messaging, Rich Links and Close
A43: 4. Core Messaging, Rich Links and Close | B43: 4.1 | C43: Rich Links used for all URLs | D43: Review every message containing a URL, from the bot and from live agents. | E43: All URLs are sent as Rich Links. Plain-text and "tap-to-load" text links are not used anywhere. | F43: 2.7 | G43: Always | H43: Non negotiable | I43: Not Started
A44: 4. Core Messaging, Rich Links and Close | B44: 4.2 | C44: Rich Link logo image is properly sized | D44: Inspect the image used for any Rich Link built from a logo. | E44: Image is square or a rectangle with width under 150px, so it renders as a clean icon rather than a cropped or blurry preview. | F44: 2.7 | G44: Always | H44: Apple standard | I44: Not Started
A45: 4. Core Messaging, Rich Links and Close | B45: 4.3 | C45: Rich Link preview asset meets Apple's specification | D45: Inspect the preview asset file for a content Rich Link. | E45: PNG, optimised at 240 by 240 pixels, up to 200 kB. This is separate from the 150 pixel icon ceiling. | F45: 2.7 | G45: Always | H45: Apple standard | I45: Not Started
A46: 4. Core Messaging, Rich Links and Close | B46: 4.4 | C46: Every Rich Link image reflects the destination page | D46: Open each Rich Link and compare the preview image to the page it opens. | E46: The image reflects the page content rather than being a generic logo placeholder. Where the destination has no Open Graph image, one is generated before sending. | F46: 2.7 | G46: Always | H46: Apple standard | I46: Not Started
A47: 4. Core Messaging, Rich Links and Close | B47: 4.5 | C47: Video Rich Links have a background image | D47: Send every video Rich Link in the experience and view it on device. | E47: The preview renders with a background image. A black preview is a fast route to a review finding. | F47: 3.7 | G47: Video Rich Links in scope | H47: Field | I47: Not Started
A48: 4. Core Messaging, Rich Links and Close | B48: 4.6 | C48: Maps and Apple Music are sent through Construct Payload | D48: Trigger any flow that shares a location or a music link. | E48: Maps and Apple Music are sent as Construct Payload, not as a Rich Link. | F48: 2.7 | G48: Maps or Music in scope | H48: Apple standard | I48: Not Started
A49: 4. Core Messaging, Rich Links and Close | B49: 4.7 | C49: Rich Link is followed by a message or call to action | D49: Send a Rich Link and observe what follows. | E49: A follow-up message with a clear call to action follows the Rich Link. It is not left to sit on its own. | F49: 2.6 | G49: Always | H49: Apple standard | I49: Not Started
A50: 4. Core Messaging, Rich Links and Close | B50: 4.8 | C50: Unclassified input never lands in silence | D50: Send one unclear or unsupported input and observe the immediate response. | E50: The bot never stays silent. It responds with a clear, polite recovery message and a way forward. (Branch-level dead ends are tested separately at 10.7.) | F50: 2.4 | G50: Always | H50: Non negotiable | I50: Not Started
A51: 4. Core Messaging, Rich Links and Close | B51: 4.9 | C51: "Anything else?" close prompt | D51: Complete a use case end to end and observe the closing message. | E51: Bot asks if the user needs further assistance, optionally with a follow-up Quick Reply, rather than abruptly ending the flow. | F51: 2.3 | G51: Always | H51: Apple standard | I51: Not Started
A52: 4. Core Messaging, Rich Links and Close | B52: 4.10 | C52: No prohibited closing phrases | D52: Review all conversation-ending copy. | E52: Phrases like "This conversation has been closed", "Finish conversation", "Messaging rates may apply" and "Data rates may apply" are not used. Closing language leaves the door open for future contact. | F52: 2.10 | G52: Always | H52: Apple standard | I52: Not Started
A53: 4. Core Messaging, Rich Links and Close | B53: 4.11 | C53: No repeated requests for information already given | D53: Provide information such as name or email earlier in the flow, then continue to a step that would normally ask for it again. | E53: The bot does not ask the user to repeat information already captured earlier in the conversation. | F53: 2.3 | G53: Always | H53: Apple standard | I53: Not Started
A54: 4. Core Messaging, Rich Links and Close | B54: 4.12 | C54: Proper casing throughout | D54: Review all message copy. | E54: All messages use proper casing. Messages sent entirely in lowercase are flagged as poor customer experience regardless of brand voice. | F54: 3.6 | G54: Always | H54: Field | I54: Not Started
A55: 4. Core Messaging, Rich Links and Close | B55: 4.13 | C55: Quick Reply summaryText is a short label | D55: Review the summary text each Quick Reply echoes back into the transcript. | E55: summaryText is short and label-based, for example "Option selected". It does not repeat the full previous message and is never used as the introduction to the Quick Reply. | F55: 2.6 | G55: Quick Reply in scope | H55: Apple standard | I55: Not Started
A56: 5. Interactive Features
A57: 5. Interactive Features | B57: 5.1 | C57: Every interactive option carries a thumbnail or icon | D57: Review every receivedMessage, replyMessage, and each individual option in a List Picker. | E57: Each includes a thumbnail image or icon making it clearly recognizable as a tappable UI element. SF Symbols where symbols are used. | F57: 2.6 | G57: Any interactive feature in scope | H57: Apple standard | I57: Not Started
A58: 5. Interactive Features | B58: 5.2 | C58: The rich card itself carries its own image | D58: Inspect the card that carries each interactive element, separately from the row thumbnails. | E58: The card has an image of its own. Row thumbnails do not satisfy this. A Form splash screen needs one too. This is the single most commonly missed rule. | F58: 2.6 | G58: Any interactive feature in scope | H58: Non negotiable | I58: Not Started
A59: 5. Interactive Features | B59: 5.3 | C59: No brand card image forced onto Apple Pay or Authentication | D59: Inspect the Apple Pay sheet and the Authentication card. | E59: Neither carries a brand card image. Both render with Apple's own supplied iconography. | F59: 2.6 | G59: Apple Pay or Authentication in scope | H59: Apple standard | I59: Not Started
A60: 5. Interactive Features | B60: 5.4 | C60: List Picker versus Quick Reply used appropriately | D60: Review each menu presented to the user. | E60: List Pickers are used only where there is genuine category variation. Five or fewer flat options use a Quick Reply instead. Bounded questions are answered by a Quick Reply rather than typed text. | F60: 2.6 | G60: List Picker in scope | H60: Apple standard | I60: Not Started
A61: 5. Interactive Features | B61: 5.5 | C61: List Picker items carry subtitles and secondary text | D61: Review the rows of every List Picker. | E61: Rows show a subtitle, and second or third subtitle lines where the choice needs them, so each row can be told apart at a glance. Titles alone force the customer to guess. Visible copy stays short; the rendered string caps near 200 characters. | F61: 2.6 | G61: List Picker in scope | H61: Apple standard | I61: Not Started
A62: 5. Interactive Features | B62: 5.6 | C62: Forms include splash screen, title, intro and review screen | D62: Step through every Form Message in the experience. | E62: Each form has a splash screen, a title, an introductory description, and a final review screen before submission. | F62: 2.6 | G62: Form in scope | H62: Apple standard | I62: Not Started
A63: 5. Interactive Features | B63: 5.7 | C63: The Form review page sits at the end of the final section | D63: Step through a multi-page Form to the end. | E63: The Review button sits at the end of the final section to be filled, not in the middle of the flow. | F63: 2.6 | G63: Multi-page Form in scope | H63: Apple standard | I63: Not Started
A64: 5. Interactive Features | B64: 5.8 | C64: Form context set in a conversational bubble first | D64: Review the message immediately preceding each form. | E64: The "why" for the form is stated in a conversational bubble before the form opens, not buried in the form's subtitle where it can be cropped. | F64: 2.6 | G64: Form in scope | H64: Apple standard | I64: Not Started
A65: 5. Interactive Features | B65: 5.9 | C65: Simple one or two field forms use plain text conversational flow | D65: Identify any form collecting only one or two fields, such as name and email. | E65: A plain-text conversational exchange is used instead of a formal Form object. | F65: 3.4 | G65: Form in scope | H65: Field | I65: Not Started
A66: 5. Interactive Features | B66: 5.10 | C66: Sensitive Form responses are marked private | D66: Inspect the payload for any form field taking sensitive data. | E66: Responses that carry sensitive data are marked private. | F66: 2.5 | G66: Form taking sensitive data | H66: Apple standard | I66: Not Started
A67: 5. Interactive Features | B67: 5.11 | C67: Introductory text precedes every rich element | D67: Observe the message immediately before every Time Picker, List Picker, Form, Quick Reply, Rich Link, Authentication card and Apple Pay request. | E67: A brief conversational message sets expectations before the interactive bubble appears. This includes Authentication and Apple Pay, for example "Please log into your account" before the Authentication card. | F67: 2.6 | G67: Any interactive feature in scope | H67: Non negotiable | I67: Not Started
A68: 5. Interactive Features | B68: 5.12 | C68: Time Picker confirmation includes a save-to-calendar tip | D68: Complete a booking flow through a Time Picker. | E68: The confirmation message tells the user they can tap their selected time to save it to their Apple Calendar. | F68: 2.6 | G68: Time Picker in scope | H68: Apple standard | I68: Not Started
... A72: 5. Interactive Features | B72: 5.16 | C72: Long text kept outside feature bubbles | D72: Review any feature bubble containing more than a short label. | E72: Long text is sent as a separate message outside the bubble. The first line of any feature bubble is its title, since longer text gets cropped. | F72: 2.6 | G72: Any interactive feature in scope | H72: Apple standard | I72: Not Started
A73: 6. Attachments and Wallet Passes
A74: 6. Attachments and Wallet Passes | B74: 6.1 | C74: Attachments render correctly and are relevant | D74: Trigger every flow that sends an image, PDF, or other attachment. | E74: Attachment renders correctly on-device and is directly relevant to the step in the flow. | F74: 2.5 | G74: Attachments in scope | H74: Apple standard | I74: Not Started
A75: 6. Attachments and Wallet Passes | B75: 6.2 | C75: Wallet passes generate and add correctly | D75: Trigger a flow that issues a Wallet pass and tap to add it. | E75: Pass generates with correct details and adds to Apple Wallet end to end without errors. | F75: 2.5 | G75: Wallet passes in scope | H75: Apple standard | I75: Not Started
A76: 7. Authentication, Apple Pay and Personal Data
A77: 7. Authentication, Apple Pay and Personal Data | B77: 7.1 | C77: Authentication used for identity verification | D77: Trigger a flow requiring identity or login verification. | E77: The Authentication message type with inline OAuth 2.0 and password autofill is used, rather than collecting credentials as plain chat text. | F77: 2.8 | G77: Authentication in scope | H77: Apple standard | I77: Not Started
A78: 7. Authentication, Apple Pay and Personal Data | B78: 7.2 | C78: Authentication precedes any account data being shared | D78: Ask for an order status, an account detail or a balance without signing in first. | E78: No order detail, account data or balance is returned until the customer has authenticated. This is a positive obligation, not only a prohibition. | F78: 2.8 | G78: Account data in scope | H78: Apple standard | I78: Not Started
A79: 7. Authentication, Apple Pay and Personal Data | B79: 7.3 | C79: Apple Pay used for payment collection | D79: Trigger a flow that requires payment. | E79: Apple Pay is used to collect payment. Full card numbers are never requested as plain text. | F79: 2.8 | G79: Apple Pay in scope | H79: Apple standard | I79: Not Started
A80: 7. Authentication, Apple Pay and Personal Data | B80: 7.4 | C80: Personal data request is gated by a clarifying question | D80: Trigger a flow that asks for name, email or contact details. | E80: A yes or no clarifying question precedes the request, for example "Is your inquiry related to your account with us?". Details are collected only on a yes. | F80: 2.8 | G80: Always | H80: Apple standard | I80: Not Started
A81: 7. Authentication, Apple Pay and Personal Data | B81: 7.5 | C81: Data collection prompts use the QuickType phrasings | D81: Read the exact wording of every prompt asking for customer data. | E81: Prompts use Apple's phrasings exactly, so iOS surfaces a QuickType suggestion and no typing is required. | F81: 2.8 | G81: Always | H81: Apple standard | I81: Not Started
A82: 7. Authentication, Apple Pay and Personal Data | B82: 7.6 | C82: No health data collected, echoed, or stored | D82: Trigger a flow where a user might disclose a health condition or diagnosis. | E82: The bot declines to engage with the health detail, does not echo it back, and nothing is logged or stored downstream. Confirm this explicitly with the client rather than assuming. | F82: 2.11 | G82: Always | H82: Non negotiable | I82: Not Started
A83: 7. Authentication, Apple Pay and Personal Data | B83: 7.7 | C83: Privacy Policy and Terms of Use are Rich Links, sent only twice | D83: Trigger a first engagement, then a second and third conversation. | E83: Both are sent as Rich Links to the brand's webpage, never pasted inline, and only on first engagement or after a policy update. Never at the start of every conversation. | F83: 2.11 | G83: Always | H83: Apple standard | I83: Not Started
A84: 7. Authentication, Apple Pay and Personal Data | B84: 7.8 | C84: No sensitive data is ever requested as plain text | D84: Walk every flow that collects customer data, and review the agent console templates as well as the bot flows. | E84: No full card number, no government ID number, no full social security number and no account password is requested in the thread. Identity goes through Authentication, payment through Apple Pay, and structured sensitive intake through a Form with private responses. | F84: 2.8 | G84: Where sensitive data is collected | H84: Non negotiable | I84: Not Started
A85: 8. Device Capability and Fallback
A86: 8. Device Capability and Fallback | B86: 8.1 | C86: Fallback happens automatically and live | D86: Run the same use case on an unsupported device or OS version. | E86: The experience swaps live, at send time, to a supported alternative, demonstrated on-device rather than described. | F86: Doc 4 | G86: Always | H86: Non negotiable | I86: Not Started
A87: 8. Device Capability and Fallback | B87: 8.2 | C87: Fallback path is not a dead end | D87: Reach the fallback path and attempt to continue the use case. | E87: The user can still complete or meaningfully progress the use case through the fallback path. | F87: Doc 4 | G87: Always | H87: Non negotiable | I87: Not Started
A88: 8. Device Capability and Fallback | B88: 8.3 | C88: Capability data is read on every inbound, not cached once | D88: Send from one device, then send from a second device on the same Apple ID with different capabilities. | E88: The capability list is parsed on every inbound message and the most recent value is stored against the device, so a device switch changes what can be sent. | F88: Doc 4 | G88: Always | H88: Apple standard | I88: Not Started
A89: 8. Device Capability and Fallback | B89: 8.4 | C89: The console cannot send what the device will not render | D89: In the agent console, open a conversation with a device that lacks a feature in scope. | E89: The unsupported option is hidden or hard disabled for that recipient, so an agent cannot send something the device cannot render. | F89: 2.3 | G89: Live agent in scope | H89: Apple standard | I89: Not Started
A90: 8. Device Capability and Fallback | B90: 8.5 | C90: The fallback decision tree is documented | D90: Ask to see the written fallback tree, not only its behaviour on device. | E90: A documented tree exists covering every interactive type in scope: the preferred type, the fallback type or sequence, the OS floor that triggers it, and the customer facing copy variant. It is versioned and kept current. Reviewers may ask to see the tree itself. | F90: 2.9 note | G90: Always | H90: Apple standard | I90: Not Started
A91: 9. Human Escalation and Live Agent Handoff
A92: 9. Human Escalation and Live Agent Handoff | B92: 9.1 | C92: Handoff to a live agent is explicitly stated | D92: Trigger escalation to a live agent. | E92: The transition is explicitly communicated, and the agent introduces themselves on joining. The reason for the transfer is given. | F92: 2.3 | G92: Live agent in scope | H92: Non negotiable | I92: Not Started
A93: 9. Human Escalation and Live Agent Handoff | B93: 9.2 | C93: Wait time is communicated | D93: Trigger escalation when no agent is immediately available. | E93: An estimated wait time is communicated, with queue position where available. | F93: 2.3 | G93: Live agent in scope | H93: Apple standard | I93: Not Started
A94: 9. Human Escalation and Live Agent Handoff | B94: 9.3 | C94: Key details are collected before escalation | D94: Escalate mid-task and observe what the agent receives. | E94: Essential information is gathered before routing, so the agent can help without re-asking. | F94: 2.3 | G94: Live agent in scope | H94: Apple standard | I94: Not Started
A95: 9. Human Escalation and Live Agent Handoff | B95: 9.4 | C95: An in conversation message is the first option when no agent is available | D95: Request a person while the team is offline or at capacity. | E95: Leaving a message in the conversation is offered first, with a stated response window. Callback and email are offered afterwards, never as the first option. | F95: 2.3 | G95: Live agent in scope | H95: Apple standard | I95: Not Started
A96: 9. Human Escalation and Live Agent Handoff | B96: 9.5 | C96: Out-of-hours escalation stays in-thread | D96: Request a live agent outside business hours. | E96: The user can leave a message within the current thread. They are not forced out to an external email system, and an agent replies to that message in the same thread. | F96: 2.3 | G96: Always | H96: Apple standard | I96: Not Started
A97: 9. Human Escalation and Live Agent Handoff | B97: 9.6 | C97: Contextual escalation stays in-channel | D97: Trigger a flow where an email to support would be drafted on the user's behalf. | E97: The bot helps compose the email within the channel rather than abruptly shifting the user away from the conversation. | F97: 3.5 | G97: Email escalation in scope | H97: Field | I97: Not Started
A98: 9. Human Escalation and Live Agent Handoff | B98: 9.7 | C98: First response service level is documented | D98: Confirm with the client what the committed first-response time for a live agent is. | E98: A specific figure is documented and available to reference if Apple asks. | F98: 2.15 | G98: Live agent in scope | H98: Apple standard | I98: Not Started
A99: 9. Human Escalation and Live Agent Handoff | B99: 9.8 | C99: The agent console experience is good on both sides | D99: Sit with an agent through a real escalation and watch both the console and the device. | E99: The customer feels responsiveness. The agent can read the thread easily and send what the conversation needs, including rich elements, without friction. A slow or awkward console shows up on the customer's screen as silence and plain text. | F99: 2.3 | G99: Live agent in scope | H99: Apple standard | I99: Not Started
A100: 9. Human Escalation and Live Agent Handoff | B100: 9.9 | C100: The escalation acknowledgement states a specific commitment | D100: Escalate, choose the offered path, and read the acknowledgement message. | E100: The confirmation states what happens next and when, with a specific figure, for example "a team member will call you within two business hours". A vague acknowledgement such as "someone will be in touch" is a review finding. | F100: 2.3 | G100: Live agent in scope | H100: Apple standard | I100: Not Started
A101: 10. Policy, Consent and Conversational Design
A102: 10. Policy, Consent and Conversational Design | B102: 10.1 | C102: Opt-in captured before non-transactional notifications | D102: Reach any flow that would enroll the customer in ongoing automated notifications. | E102: Explicit opt-in is captured as an active tap before enrollment, and the record persists brand, channel, purpose, destination, source, timestamp and disclosure version. | F102: 2.9 | G102: Notifications in scope | H102: Non negotiable | I102: Not Started
A103: 10. Policy, Consent and Conversational Design | B103: 10.2 | C103: The enrolment template carries its own opt out instruction | D103: Read the enrolment and confirmation message templates. | E103: The opt out instruction sits in the template itself, not only in the moment of consent. Apple's shape: welcome, brand name, automated disclosure, then "Reply STOP anytime to turn off notifications." | F103: 2.9 | G103: Notifications in scope | H103: Apple standard | I103: Not Started
A104: 10. Policy, Consent and Conversational Design | B104: 10.3 | C104: STOP re-entry shows a "Welcome back" message | D104: Opt out via STOP, then message the brand again to re-subscribe. | E104: The bot recognizes the re-entry and responds with a "Welcome back" style message. | F104: 2.9 | G104: Notifications in scope | H104: Apple standard | I104: Not Started
A105: 10. Policy, Consent and Conversational Design | B105: 10.4 | C105: Restarting restores reply permission, not notification consent | D105: Opt out of notifications, then start a fresh conversation and complete a task. | E105: The brand may reply inside that conversation. It may not resume notifications. The two states reset separately. | F105: 2.9 | G105: Notifications in scope | H105: Apple standard | I105: Not Started
A106: 10. Policy, Consent and Conversational Design | B106: 10.5 | C106: Satisfaction survey timing and format | D106: Complete an individual FAQ interaction, then complete a full end-to-end use case, then close a conversation. Review the survey itself. | E106: A survey fires only after a real resolution. Not after every FAQ answer, not before the task is resolved, and never after a close, a Leave Conversation or an opt out. It uses descriptive labels rather than a bare one to five scale, delivered as a Quick Reply, or a Form Message for a multi question survey. | F106: 2.10 | G106: Survey in scope | H106: Apple standard | I106: Not Started
A107: 10. Policy, Consent and Conversational Design | B107: 10.6 | C107: Channel constraints on unsolicited surveys respected | D107: Check whether the brand has a protective agreement affecting unsolicited messages to its end users, for example school districts and parent inboxes. | E107: Where such agreements exist, survey timing is controlled by the brand or institution rather than fired automatically. | F107: 2.10 | G107: Survey in scope | H107: Field | I107: Not Started
A108: 10. Policy, Consent and Conversational Design | B108: 10.7 | C108: No dead ends anywhere in the flow | D108: Walk every branch of the conversation design, including error and edge-case paths. (Single unclassified inputs are tested at 4.8.) | E108: Every path has a clear next step, a fallback, or an escalation route. Never a dead end. | F108: 2.4 | G108: Always | H108: Non negotiable | I108: Not Started
A109: 10. Policy, Consent and Conversational Design | B109: 10.8 | C109: No unsolicited outbound | D109: Review every outbound path the platform can fire: campaigns, scheduled sends, retries, replays, notification jobs and agent console templates. Attempt an outbound to a customer with no open conversation and no accepted invitation. | E109: Outbound is only sent inside an ongoing customer initiated conversation, or through an approved Business Invitation template. No SMS style marketing blasts and no unsolicited sends. Reviewers actively look for this. | F109: 2.9 | G109: Always | H109: Non negotiable | I109: Not Started
A110: 11. Recording and Submission Prep
...

Sheet Legend
B2: Legend and instructions
B4: How to use this template
B5: 1. Duplicate all five tabs for each new client or brand experience. Summary and Checklist read each other by name, so keep them together.
B6: 2. Fill in Appendix A first. It is the scope agreement, and it decides which rows apply. Appendix B is completed at the same stage but tests nothing.
B7: 3. Work through the Checklist against the live build. Use the Status dropdown in column I.
B8: 4. Mark a row N/A where the Applies when condition is not met on Appendix A.
B9: 5. Log evidence in column J as video and timestamp, for example V1 04:12. Exporting that column gives you the timestamp index Apple asks for alongside the recordings.
B10: 6. Summary rolls up automatically. Formulas recalculate on open.
B11: 7. Section 0 is a final pre-submission gate, not a re-test. It holds only the items not duplicated elsewhere. See the mapping below.
B13: The two appendices
B14: Appendix A and Appendix B reproduce Apple's own brand facing forms, Messages for Business Use Cases and Messages for Business Readiness Review. Apple recommends that brands complete both at the start of the engagement. They are included here so the answers sit alongside the tests they govern. Appendix A drives which rows apply. Appendix B is commercial and operational qualification and tests nothing against the build.
B16: Apple's five non-negotiables, and where each is tested
B17: Live agent escalation reachable, or the exempted path | C17: 0.1, and Section 9
B18: Opt-out works end to end | C18: 0.4, and 10.8
B19: No personal data requested in plain conversation | C19: 7.4 and 7.8
B20: Consent captured before any opt-in notification | C20: 10.1 and 10.2
B21: Capability aware fallback | C21: 8.1, 8.2 and 8.5
B22: Section 0 also carries two further gate items that are not among Apple's five but fail a review on their own: Leave Conversation respected (0.2) and no forbidden or restricted platform wording (0.3).
B24: Status values
B25: Not Started | C25: Not yet tested
B26: In Progress | C26: Testing underway
B27: Pass | C27: Meets the expected result
B28: Fail | C28: Does not meet the expected result
B29: Blocked | C29: Cannot be tested yet
B30: N/A | C30: Applies when condition not met for this build
B31: Requires client testing | C31: Only the client can verify, for example agent training
B32: TBD | C32: Scope or expectation not yet agreed
B34: Severity
B35: Non negotiable | C35: Checked on every Apple review. A failure blocks submission.
B36: Apple standard | C36: A documented Apple requirement. A failure is very likely to be returned.
B37: Field | C37: A Messaging Advisory observation. A failure is a quality risk, not an Apple rule.
B39: Reading the Ref column
B40: A reference shown in blue is new in this version. Rule ref points at the section of Document 2, the Conversation Design Standards and Best Practices, that the row tests. Doc 1 and Doc 4 references point at the Process Overview and the Recording Guide.
B42: Version and sources
B43: Template version | C43: 2.0
B44: Date | C44: 31 August 2026
B45: Derived from | C45: Conversation Design Standards and Best Practices v2.1
B46: Scope tab mirrors | C46: Apple, Messages for Business Use Cases form
B47: Previous version | C47: 63 test cases, 12 sections
B48: This version | C48: 114 test cases, 13 sections: 54 carried unchanged, 10 reworded or widened, 50 new
B49: Also derived from | C49: Experience items in the MSP Integration Checklist, Apple Feedback Update 25 August 2026

Sheet Apple Appendix A Scope
B6: Appendix A. Use case scope
B7: Apple, Messages for Business Use Cases
B8: This mirrors Apple's own Use Cases form, which Apple asks brands to complete at the start of the engagement. Reproduced here so the answers sit alongside the tests they govern.
B9: Fill the shaded cells. What you record here is the scope for the Checklist and the shot list for the recordings. Every 'Applies when' condition on the Checklist reads against it.
B11: Company information
B13: Brand name
B14: Definition of success | D14: One major achievement this channel should deliver
B15: Requested launch date
B16: Provider or MSP
B18: Entry points in scope
B20: Website Messages button | C20: No
B21: Message Suggest | C21: No | D21: Registered phone numbers, allow 5 to 7 days to propagate
B22: App Messages button | C22: No
B23: Social media links | C23: No
B24: IVR deflection | C24: No
B25: Apple Maps | C25: No
B26: QR codes | C26: No
B27: Wallet passes | C27: No
B28: Business Invitations | C28: No | D28: Drives rows 2.3, 2.4, 2.5
B29: Other, specify | C29: No
B31: General features in scope
B33: Automated welcome message | C33: No
B34: Satisfaction survey | C34: No | D34: Drives rows 10.5, 10.6
B35: Authentication | C35: No | D35: Drives rows 5.3, 7.1, 7.2
B36: Notifications and enrolment | C36: No | D36: Drives Section 10
B37: Live agent | C37: No | D37: Drives Section 9, and rows 1.5, 3.7, 8.4
B38: Multilingual | C38: No | D38: Drives rows 3.16, 3.17
B39: Account data returned in conversation | C39: No | D39: Drives row 7.2
B41: Enhanced features in scope
B43: Quick Reply | C43: No | D43: Drives row 4.13
B44: List Picker | C44: No | D44: Drives rows 5.4, 5.5
B45: Time Picker | C45: No | D45: Drives rows 5.12, 5.13
B46: Form | C46: No | D46: Drives rows 5.6 to 5.10
B47: Apple Pay | C47: No | D47: Drives rows 5.3, 7.3
B48: Rich Links | C48: No
B49: Video Rich Links | C49: No | D49: Drives row 4.5
B50: Maps or Apple Music payloads | C50: No | D50: Drives row 4.6
B51: Embedded app experience | C51: No
B52: Attachments: PDF, image, video | C52: No | D52: Drives row 6.1
B53: Wallet passes issued in conversation | C53: No | D53: Drives row 6.2
B55: Use cases
B57: Use case 1 | D57: Description, and the enhanced features it uses
B58: Use case 2 | D58: Description, and the enhanced features it uses
B59: Use case 3 | D59: Description, and the enhanced features it uses
B60: Use case 4 | D60: Description, and the enhanced features it uses

Sheet Apple Appendix B Readiness
B2: Appendix B. Readiness Review
B3: Apple, Messages for Business Readiness Review
B4: This mirrors Apple's own Readiness Review form, which Apple asks brands to complete before scope alignment. It qualifies the channel commercially and operationally. Nothing here is tested against a build.
B5: Fill the shaded cells. The containment figure and the cost per inquiry bands are the two answers Apple returns to most often, so give real numbers.
B7: Company information
B9: Brand name
B10: Industry vertical
B11: Country of headquarters
B12: Country coverage
B14: Digital priorities
B16: Digital deflection from the contact centre to self serve tools | D16: High, Medium or Low
B17: Driving consumer iOS app adoption | D17: High, Medium or Low
B18: Increasing customer experience metrics | D18: High, Medium or Low
B19: Reducing operational cost to sell and serve customers | D19: High, Medium or Low
B20: General call deflection from voice to digital channels | D20: High, Medium or Low
B21: Digital shift from web or live chat to asynchronous messaging | D21: High, Medium or Low
B22: Creating a digital sales engagement channel | D22: High, Medium or Low
B23: Improving collaboration between the contact centre and physical store or branch locations | D23: High, Medium or Low
B24: Securing conversation history for regulatory and internal audit purposes | D24: High, Medium or Low
B26: Strategy and operations
B28: A digital messaging platform is already in place | C28: No | D28: If yes, name the vendor in the notes column
B29: The digital messaging strategy is defined and executive sponsored | C29: No
B30: The business already engages customers in live or asynchronous messaging | C30: No
B31: The strategy includes AI or automation led conversations | C31: No | D31: If yes, state the anticipated containment percentage
B33: Volume and economics
B35: Anticipated containment from conversational AI | D35: Percentage
B36: Expected daily conversation capacity at launch
B37: Growth goal, daily conversations at 12 months
B38: Growth goal, daily conversations at 24 months
B39: Cost per inquiry, voice | D39: Band: 1 to 3, 4 to 8, 9 to 12, 12 plus
B40: Cost per inquiry, digital | D40: Band: 1 to 3, 4 to 8, 9 to 12, 12 plus
B41: Share of the digital customer base on Apple devices | D41: Under 50%, 50 to 75%, over 75%
B42: Live agents dedicated exclusively to this channel | D42: Yes or No
